pcr/__init__.py
pcr/args_cli.py
pcr/client_http.py
pcr/plugin.py
pytest_chic_report-2.0.3.dist-info/METADATA
pytest_chic_report-2.0.3.dist-info/WHEEL
pytest_chic_report-2.0.3.dist-info/entry_points.txt
pytest_chic_report-2.0.3.dist-info/top_level.txt
pytest_chic_report-2.0.3.dist-info/RECORD
