Metadata-Version: 2.1
Name: pytest-chic-report
Version: 2.0.3
Summary: Simple pytest plugin for generating and sending report to messengers.
Author-email: Oleg Matskiv <alpaca00tuha@gmail.com>
License: MIT
Keywords: pytest,report,messenger,teams,slack
Requires-Python: >=3.8
Requires-Dist: pytest>=6.0
